adt_extension/Set.py
adt_extension/SwitchDict.py
adt_extension/__init__.py
adt_extension-0.2.0.dist-info/METADATA
adt_extension-0.2.0.dist-info/WHEEL
adt_extension-0.2.0.dist-info/top_level.txt
adt_extension-0.2.0.dist-info/RECORD
